{
	"format_version": "1.20.80",
	"minecraft:recipe_shaped": {
		"description": {
			"identifier": "twm:golden_paxel"
		},
		"tags": [
			"utility_table"
		],
		"pattern": [
			"AXA",
			"ZSC",
			"DSD"
		],
		"key": {
			"A": {
				"item": "minecraft:slime_ball"
			},
			"X": {
				"item": "minecraft:golden_shovel"
			},
			"Z": {
				"item": "minecraft:golden_axe"
			},
			"S": {
				"item": "minecraft:stick"
			},
			"C": {
				"item": "minecraft:golden_pickaxe"
			},
			"D": {
				"item": "minecraft:string"
			}
		},
		"unlock": [
			{
				"item": "minecraft:slime_ball"
			},
			{
				"item": "minecraft:golden_shovel"
			},
			{
				"item": "minecraft:golden_axe"
			},
			{
				"item": "minecraft:stick"
			},
			{
				"item": "minecraft:golden_pickaxe"
			},
			{
				"item": "minecraft:string"
			}
		],
		"result": [
			{
				"item": "twm:golden_paxel"
			}
		]
	}
}